src/__init__.py
src/logging.py
tests/__init__.py
tests/test_check_versions.py
tests/test_logging.py
kom_python_logging-0.6.dist-info/METADATA
kom_python_logging-0.6.dist-info/WHEEL
kom_python_logging-0.6.dist-info/top_level.txt
kom_python_logging-0.6.dist-info/RECORD
