Metadata-Version: 2.1
Name: kom-python-logging
Version: 0.6
Summary: A logging package for Python applications
Home-page: https://github.com/KominskyOrg/kom-python-logging
Author: Jared Kominsky
Author-email: 83463012+jaredkominsky@users.noreply.github.com
Classifier: Programming Language :: Python :: 3
Classifier: License :: OSI Approved :: MIT License
Classifier: Operating System :: OS Independent
Requires-Python: >=3.6
